mgtoolkit/__init__.py
mgtoolkit/cli.py
mgtoolkit/console_script.py
mgtoolkit/enums.py
mgtoolkit/exception.py
mgtoolkit/library.py
mgtoolkit/mgtoolkit.py
mgtoolkit/properties.py
mgtoolkit-1.1.3.dist-info/AUTHORS.rst
mgtoolkit-1.1.3.dist-info/LICENSE
mgtoolkit-1.1.3.dist-info/METADATA
mgtoolkit-1.1.3.dist-info/WHEEL
mgtoolkit-1.1.3.dist-info/entry_points.txt
mgtoolkit-1.1.3.dist-info/top_level.txt
mgtoolkit-1.1.3.dist-info/zip-safe
mgtoolkit-1.1.3.dist-info/RECORD
